README.md
setup.py
dbtlogs/__init__.py
dbtlogs/main.py
dbtlogs12.egg-info/PKG-INFO
dbtlogs12.egg-info/SOURCES.txt
dbtlogs12.egg-info/dependency_links.txt
dbtlogs12.egg-info/entry_points.txt
dbtlogs12.egg-info/requires.txt
dbtlogs12.egg-info/top_level.txt